IOTCommon/DatabaseLayer.py
IOTCommon/Operations.py
IOTCommon/__init__.py
IOTCommon/helperhttps.py
Module/DatabaseLayer.py
Module/Operations.py
Module/__init__.py
Module/helperhttps.py
IOTCommon-0.1.2.dist-info/METADATA
IOTCommon-0.1.2.dist-info/WHEEL
IOTCommon-0.1.2.dist-info/top_level.txt
IOTCommon-0.1.2.dist-info/RECORD
