Metadata-Version: 2.1
Name: IOTCommon
Version: 0.1.2
Summary: Common operations for sweiot microservices
Home-page: https://github.com/AntonNPersson/SweIoTServices.git
Author: Anton Persson
Author-email: Antonnilspersson@gmail.com
Classifier: Programming Language :: Python :: 3
Classifier: Operating System :: OS Independent
Requires-Dist: click (==8.1.3)
Requires-Dist: colorama (==0.4.6)
Requires-Dist: Flask (==2.2.3)
Requires-Dist: greenlet (==2.0.2)
Requires-Dist: itsdangerous (==2.1.2)
Requires-Dist: Jinja2 (==3.1.2)
Requires-Dist: MarkupSafe (==2.1.2)
Requires-Dist: SQLAlchemy (==2.0.9)
Requires-Dist: typing-extensions (==4.5.0)
Requires-Dist: Werkzeug (==2.2.3)
